uji.py
uji-0.1.data/data/share/man/man1/uji.1
uji-0.1.dist-info/LICENSE
uji-0.1.dist-info/METADATA
uji-0.1.dist-info/WHEEL
uji-0.1.dist-info/entry_points.txt
uji-0.1.dist-info/top_level.txt
uji-0.1.dist-info/RECORD
