Metadata-Version: 2.1
Name: uji
Version: 0.1
Summary: Test log tracker
Home-page: http://github.com/whot/uji
Author: The uji authors
Author-email: check.the@git.history
License: MIT
Platform: UNKNOWN
Classifier: Development Status :: 3 - Alpha
Classifier: License :: OSI Approved :: GNU General Public License v2 or later (GPLv2+)
Classifier: Programming Language :: Python :: 3
Classifier: Programming Language :: Python :: 3.6
Requires-Python: >=3.6
Requires-Dist: pyyaml
Requires-Dist: GitPython
Requires-Dist: click
Requires-Dist: curtsies
